jaqalpaq/_cli.py
jaqalpaq/_import.py
jaqalpaq/error.py
jaqalpaq/utilities.py
jaqalpaq/core/__init__.py
jaqalpaq/core/block.py
jaqalpaq/core/branch.py
jaqalpaq/core/circuit.py
jaqalpaq/core/circuitbuilder.py
jaqalpaq/core/constant.py
jaqalpaq/core/gate.py
jaqalpaq/core/gatedef.py
jaqalpaq/core/identifier.py
jaqalpaq/core/locus.py
jaqalpaq/core/macro.py
jaqalpaq/core/parameter.py
jaqalpaq/core/register.py
jaqalpaq/core/stretch.py
jaqalpaq/core/usepulses.py
jaqalpaq/core/algorithm/__init__.py
jaqalpaq/core/algorithm/expand_macros.py
jaqalpaq/core/algorithm/expand_subcircuits.py
jaqalpaq/core/algorithm/fill_in_let.py
jaqalpaq/core/algorithm/fill_in_map.py
jaqalpaq/core/algorithm/make_subcircuits_visitor.py
jaqalpaq/core/algorithm/unit_timing.py
jaqalpaq/core/algorithm/used_qubit_visitor.py
jaqalpaq/core/algorithm/visitor.py
jaqalpaq/core/algorithm/walkers.py
jaqalpaq/emulator/__init__.py
jaqalpaq/emulator/_import.py
jaqalpaq/emulator/_validator.py
jaqalpaq/emulator/backend.py
jaqalpaq/emulator/unitary.py
jaqalpaq/emulator/pygsti/__init__.py
jaqalpaq/emulator/pygsti/backends.py
jaqalpaq/emulator/pygsti/circuit.py
jaqalpaq/emulator/pygsti/model.py
jaqalpaq/generator/__init__.py
jaqalpaq/generator/generator.py
jaqalpaq/ipc/__init__.py
jaqalpaq/ipc/client.py
jaqalpaq/ipc/header.py
jaqalpaq/ipc/server.py
jaqalpaq/parser/__init__.py
jaqalpaq/parser/identifier.py
jaqalpaq/parser/parser.py
jaqalpaq/parser/slyparse.py
jaqalpaq/qsyntax/__init__.py
jaqalpaq/qsyntax/compile.py
jaqalpaq/qsyntax/qsyntax.py
jaqalpaq/run/__init__.py
jaqalpaq/run/_view.py
jaqalpaq/run/backend.py
jaqalpaq/run/classical_cursor.py
jaqalpaq/run/cursor.py
jaqalpaq/run/frontend.py
jaqalpaq/run/result.py
jaqalpaq-1.3.0.data/data/share/jaqalpaq/examples/usage_example.py
jaqalpaq-1.3.0.data/data/share/jaqalpaq/examples/H2 (Molecular Hydrogen)/JaqalPaq_H2_Exemplar.ipynb
jaqalpaq-1.3.0.data/data/share/jaqalpaq/examples/HeH+ (Helium Hydride)/JaqalPaq_HeH+_Tapered_Exemplar.ipynb
jaqalpaq-1.3.0.dist-info/licenses/LICENSE
jaqalpaq-1.3.0.dist-info/licenses/NOTICE
jaqalpaq-1.3.0.dist-info/METADATA
jaqalpaq-1.3.0.dist-info/WHEEL
jaqalpaq-1.3.0.dist-info/entry_points.txt
jaqalpaq-1.3.0.dist-info/top_level.txt
jaqalpaq-1.3.0.dist-info/RECORD
