Metadata-Version: 2.4
Name: JaqalPaq
Version: 1.3.0
Summary: Python tools for Jaqal
Home-page: https://qscout.sandia.gov
Author: Benjamin C. A. Morrison, Jay Wesley Van Der Wall, Daniel Lobser, Antonio Russo, Kenneth Rudinger, Peter Maunz
Author-email: qscout@sandia.gov
License: Apache
Classifier: Development Status :: 4 - Beta
Classifier: Intended Audience :: Science/Research
Classifier: License :: OSI Approved :: Apache Software License
Classifier: Programming Language :: Python :: 3
Classifier: Topic :: Scientific/Engineering :: Physics
Classifier: Operating System :: Microsoft :: Windows
Classifier: Operating System :: MacOS :: MacOS X
Classifier: Operating System :: Unix
Requires-Python: >=3.6.5
License-File: LICENSE
License-File: NOTICE
Requires-Dist: sly
Provides-Extra: tests
Requires-Dist: pytest; extra == "tests"
Provides-Extra: docs
Requires-Dist: Sphinx; extra == "docs"
Requires-Dist: sphinx-rtd-theme; extra == "docs"
Requires-Dist: JaqalPaq[pygsti-integration]; extra == "docs"
Requires-Dist: JaqalPaq-extras[projectq,pyquil,pytket,qiskit]==1.3.0; extra == "docs"
Provides-Extra: pygsti-integration
Requires-Dist: pyGSTi==0.9.11.1; extra == "pygsti-integration"
Requires-Dist: numpy<2.0a0; extra == "pygsti-integration"
Provides-Extra: notebooks
Requires-Dist: openfermion; extra == "notebooks"
Requires-Dist: pyscf; extra == "notebooks"
Requires-Dist: openfermionpyscf; extra == "notebooks"
Dynamic: license-file
